shabda/1000nouns.txt
shabda/__init__.py
shabda/cache.py
shabda/chatter.py
shabda/cli.py
shabda/client.py
shabda/display.py
shabda/dj.py
shabda/sampleset.py
shabda/sound.py
shabda/templates/home.html
shabda/web.py
shabda-0.2.2.1.dist-info/METADATA
shabda-0.2.2.1.dist-info/WHEEL
shabda-0.2.2.1.dist-info/entry_points.txt
shabda-0.2.2.1.dist-info/licenses/LICENSE
shabda-0.2.2.1.dist-info/RECORD
