Metadata-Version: 2.4
Name: shabda
Version: 0.2.2.1
Summary: A semantic audio samples curator for livecoding software
License: MIT
License-File: LICENSE
Keywords: music,livecoding,tidalcycles
Author: Alexandre G.-Raymond
Author-email: alex@ndre.gr
Requires-Python: >=3.10,<4.0
Classifier: Development Status :: 4 - Beta
Classifier: Intended Audience :: End Users/Desktop
Classifier: License :: OSI Approved :: MIT License
Classifier: Programming Language :: Python :: 3
Classifier: Programming Language :: Python :: 3.10
Classifier: Programming Language :: Python :: 3.11
Classifier: Programming Language :: Python :: 3.12
Classifier: Programming Language :: Python :: 3.13
Classifier: Programming Language :: Python :: 3.14
Classifier: Topic :: Multimedia :: Sound/Audio
Requires-Dist: flask[async]
Requires-Dist: freesound-api
Requires-Dist: google-cloud-texttospeech
Requires-Dist: gunicorn
Requires-Dist: pydub
Requires-Dist: requests
Requires-Dist: termcolor
Requires-Dist: typer[all]
Project-URL: Bug Tracker, https://github.com/ilesinge/shabda/issues
Project-URL: Homepage, https://shabda.ndre.gr/
Project-URL: Repository, https://github.com/ilesinge/shabda
